MANIFEST.in
setup.py
graphicsx/__init__.py
graphicsx.egg-info/PKG-INFO
graphicsx.egg-info/SOURCES.txt
graphicsx.egg-info/dependency_links.txt
graphicsx.egg-info/requires.txt
graphicsx.egg-info/top_level.txt