Metadata-Version: 2.1
Name: graphicsx
Version: 0.1
Requires-Dist: requests>=2.25.1
